{
  "indexes": [
    {
      "collectionGroup": "messages",
      "queryScope": "COLLECTION",
      "fields": [
        {
          "fieldPath": "groupId",
          "order": "ASCENDING"
        },
        {
          "fieldPath": "timestamp",
          "order": "DESCENDING"
        }
      ]
    },
    {
      "collectionGroup": "events",
      "queryScope": "COLLECTION",
      "fields": [
        {
          "fieldPath": "groupId",
          "order": "ASCENDING"
        },
        {
          "fieldPath": "startDate",
          "order": "ASCENDING"
        }
      ]
    },
    {
      "collectionGroup": "expenses",
      "queryScope": "COLLECTION",
      "fields": [
        {
          "fieldPath": "groupId",
          "order": "ASCENDING"
        },
        {
          "fieldPath": "date",
          "order": "DESCENDING"
        }
      ]
    },
    {
      "collectionGroup": "friend_requests",
      "queryScope": "COLLECTION",
      "fields": [
        {
          "fieldPath": "toUserId",
          "order": "ASCENDING"
        },
        {
          "fieldPath": "status",
          "order": "ASCENDING"
        }
      ]
    }
  ],
  "fieldOverrides": []
}